ndicapy.cpython-37m-darwin.so
ndicapi-3.7.2.dist-info/LICENSE
ndicapi-3.7.2.dist-info/METADATA
ndicapi-3.7.2.dist-info/WHEEL
ndicapi-3.7.2.dist-info/top_level.txt
ndicapi-3.7.2.dist-info/RECORD
